zwdocs/__init__.py
zwdocs/__version__.py
zwdocs/pdf.py
zwdocs/utils.py
zwdocs-0.0.2.dist-info/LICENSE
zwdocs-0.0.2.dist-info/METADATA
zwdocs-0.0.2.dist-info/WHEEL
zwdocs-0.0.2.dist-info/top_level.txt
zwdocs-0.0.2.dist-info/RECORD
